{
 "custom_fields": [
  {
   "_assign": null,
   "_comments": null,
   "_liked_by": null,
   "_user_tags": null,
   "allow_on_submit": 0,
   "bold": 0,
   "collapsible": 0,
   "collapsible_depends_on": null,
   "columns": 0,
   "creation": "2021-05-28 19:43:17.961029",
   "default": null,
   "depends_on": null,
   "description": null,
   "docstatus": 0,
   "dt": "Report",
   "fetch_from": null,
   "fetch_if_empty": 0,
   "fieldname": "replica_priority",
   "fieldtype": "Select",
   "hidden": 0,
   "idx": 18,
   "ignore_user_permissions": 0,
   "ignore_xss_filter": 0,
   "in_global_search": 0,
   "in_list_view": 0,
   "in_standard_filter": 0,
   "insert_after": "timeout",
   "label": "Replica Priority",
   "modified": "2021-05-28 19:43:17.961029",
   "modified_by": "Administrator",
   "name": "Report-replica_priority",
   "no_copy": 0,
   "options": "0\n1",
   "owner": "Administrator",
   "parent": null,
   "parentfield": null,
   "parenttype": null,
   "permlevel": 0,
   "precision": "",
   "print_hide": 0,
   "print_hide_if_no_value": 0,
   "print_width": "",
   "read_only": 0,
   "regex_pattern": "",
   "report_hide": 0,
   "reqd": 0,
   "search_index": 0,
   "translatable": 1,
   "unique": 0,
   "width": ""
  },
  {
   "_assign": null,
   "_comments": null,
   "_liked_by": null,
   "_user_tags": null,
   "allow_on_submit": 0,
   "bold": 0,
   "collapsible": 0,
   "collapsible_depends_on": null,
   "columns": 0,
   "creation": "2021-04-19 16:30:33.485916",
   "default": null,
   "depends_on": null,
   "description": null,
   "docstatus": 0,
   "dt": "Report",
   "fetch_from": null,
   "fetch_if_empty": 0,
   "fieldname": "classification",
   "fieldtype": "Link",
   "hidden": 0,
   "idx": 14,
   "ignore_user_permissions": 0,
   "ignore_xss_filter": 0,
   "in_global_search": 0,
   "in_list_view": 0,
   "in_standard_filter": 0,
   "insert_after": "publish",
   "label": "Classification",
   "modified": "2021-04-19 16:30:33.485916",
   "modified_by": "Administrator",
   "name": "Report-classification",
   "no_copy": 0,
   "options": "Report Classification",
   "owner": "Administrator",
   "parent": null,
   "parentfield": null,
   "parenttype": null,
   "permlevel": 0,
   "precision": "",
   "print_hide": 0,
   "print_hide_if_no_value": 0,
   "print_width": "",
   "read_only": 0,
   "regex_pattern": "",
   "report_hide": 0,
   "reqd": 0,
   "search_index": 0,
   "translatable": 0,
   "unique": 0,
   "width": ""
  },
  {
   "_assign": null,
   "_comments": null,
   "_liked_by": null,
   "_user_tags": null,
   "allow_on_submit": 0,
   "bold": 0,
   "collapsible": 0,
   "collapsible_depends_on": null,
   "columns": 0,
   "creation": "2021-04-19 16:13:01.634422",
   "default": null,
   "depends_on": null,
   "description": null,
   "docstatus": 0,
   "dt": "Report",
   "fetch_from": null,
   "fetch_if_empty": 0,
   "fieldname": "description",
   "fieldtype": "Code",
   "hidden": 0,
   "idx": 15,
   "ignore_user_permissions": 0,
   "ignore_xss_filter": 0,
   "in_global_search": 0,
   "in_list_view": 0,
   "in_standard_filter": 0,
   "insert_after": "classification",
   "label": "Description",
   "modified": "2021-04-19 16:13:01.634422",
   "modified_by": "Administrator",
   "name": "Report-description",
   "no_copy": 0,
   "options": null,
   "owner": "Administrator",
   "parent": null,
   "parentfield": null,
   "parenttype": null,
   "permlevel": 0,
   "precision": "",
   "print_hide": 0,
   "print_hide_if_no_value": 0,
   "print_width": "",
   "read_only": 0,
   "regex_pattern": "",
   "report_hide": 0,
   "reqd": 0,
   "search_index": 0,
   "translatable": 0,
   "unique": 0,
   "width": ""
  },
  {
   "_assign": null,
   "_comments": null,
   "_liked_by": null,
   "_user_tags": null,
   "allow_on_submit": 0,
   "bold": 0,
   "collapsible": 0,
   "collapsible_depends_on": null,
   "columns": 0,
   "creation": "2021-04-18 23:25:54.358287",
   "default": null,
   "depends_on": null,
   "description": null,
   "docstatus": 0,
   "dt": "Report",
   "fetch_from": null,
   "fetch_if_empty": 0,
   "fieldname": "publish",
   "fieldtype": "Check",
   "hidden": 0,
   "idx": 13,
   "ignore_user_permissions": 0,
   "ignore_xss_filter": 0,
   "in_global_search": 0,
   "in_list_view": 0,
   "in_standard_filter": 0,
   "insert_after": "report_master_settings",
   "label": "Publish",
   "modified": "2021-04-18 23:25:54.358287",
   "modified_by": "Administrator",
   "name": "Report-publish",
   "no_copy": 0,
   "options": null,
   "owner": "Administrator",
   "parent": null,
   "parentfield": null,
   "parenttype": null,
   "permlevel": 0,
   "precision": "",
   "print_hide": 0,
   "print_hide_if_no_value": 0,
   "print_width": "",
   "read_only": 0,
   "regex_pattern": "",
   "report_hide": 0,
   "reqd": 0,
   "search_index": 0,
   "translatable": 0,
   "unique": 0,
   "width": ""
  },
  {
   "_assign": null,
   "_comments": null,
   "_liked_by": null,
   "_user_tags": null,
   "allow_on_submit": 0,
   "bold": 0,
   "collapsible": 1,
   "collapsible_depends_on": null,
   "columns": 0,
   "creation": "2021-04-18 23:25:54.228298",
   "default": null,
   "depends_on": null,
   "description": null,
   "docstatus": 0,
   "dt": "Report",
   "fetch_from": null,
   "fetch_if_empty": 0,
   "fieldname": "report_master_settings",
   "fieldtype": "Section Break",
   "hidden": 0,
   "idx": 12,
   "ignore_user_permissions": 0,
   "ignore_xss_filter": 0,
   "in_global_search": 0,
   "in_list_view": 0,
   "in_standard_filter": 0,
   "insert_after": "letter_head",
   "label": "Report Master Settings",
   "modified": "2021-04-18 23:25:54.228298",
   "modified_by": "Administrator",
   "name": "Report-report_master_settings",
   "no_copy": 0,
   "options": null,
   "owner": "Administrator",
   "parent": null,
   "parentfield": null,
   "parenttype": null,
   "permlevel": 0,
   "precision": "",
   "print_hide": 0,
   "print_hide_if_no_value": 0,
   "print_width": "",
   "read_only": 0,
   "regex_pattern": "",
   "report_hide": 0,
   "reqd": 0,
   "search_index": 0,
   "translatable": 0,
   "unique": 0,
   "width": ""
  },
  {
   "_assign": null,
   "_comments": null,
   "_liked_by": null,
   "_user_tags": null,
   "allow_on_submit": 0,
   "bold": 0,
   "collapsible": 0,
   "collapsible_depends_on": null,
   "columns": 0,
   "creation": "2020-06-19 11:38:56.887704",
   "default": "0",
   "depends_on": null,
   "description": null,
   "docstatus": 0,
   "dt": "Report",
   "fetch_from": null,
   "fetch_if_empty": 0,
   "fieldname": "cache_expiry",
   "fieldtype": "Int",
   "hidden": 0,
   "idx": 23,
   "ignore_user_permissions": 0,
   "ignore_xss_filter": 0,
   "in_global_search": 0,
   "in_list_view": 0,
   "in_standard_filter": 0,
   "insert_after": "caching_scope",
   "label": "Cache Expiry",
   "modified": "2020-06-19 11:38:56.887704",
   "modified_by": "Administrator",
   "name": "Report-cache_expiry",
   "no_copy": 0,
   "options": null,
   "owner": "Administrator",
   "parent": null,
   "parentfield": null,
   "parenttype": null,
   "permlevel": 0,
   "precision": "",
   "print_hide": 0,
   "print_hide_if_no_value": 0,
   "print_width": "",
   "read_only": 0,
   "regex_pattern": "",
   "report_hide": 0,
   "reqd": 0,
   "search_index": 0,
   "translatable": 0,
   "unique": 0,
   "width": ""
  },
  {
   "_assign": null,
   "_comments": null,
   "_liked_by": null,
   "_user_tags": null,
   "allow_on_submit": 0,
   "bold": 0,
   "collapsible": 0,
   "collapsible_depends_on": null,
   "columns": 0,
   "creation": "2020-06-19 11:38:56.774144",
   "default": null,
   "depends_on": null,
   "description": null,
   "docstatus": 0,
   "dt": "Report",
   "fetch_from": null,
   "fetch_if_empty": 0,
   "fieldname": "caching_scope",
   "fieldtype": "Select",
   "hidden": 0,
   "idx": 22,
   "ignore_user_permissions": 0,
   "ignore_xss_filter": 0,
   "in_global_search": 0,
   "in_list_view": 0,
   "in_standard_filter": 0,
   "insert_after": "acceptable_data_lag",
   "label": "Caching Scope",
   "modified": "2020-06-19 11:38:56.774144",
   "modified_by": "Administrator",
   "name": "Report-caching_scope",
   "no_copy": 0,
   "options": "User\nGlobal",
   "owner": "Administrator",
   "parent": null,
   "parentfield": null,
   "parenttype": null,
   "permlevel": 0,
   "precision": "",
   "print_hide": 0,
   "print_hide_if_no_value": 0,
   "print_width": "",
   "read_only": 0,
   "regex_pattern": "",
   "report_hide": 0,
   "reqd": 0,
   "search_index": 0,
   "translatable": 0,
   "unique": 0,
   "width": ""
  },
  {
   "_assign": null,
   "_comments": null,
   "_liked_by": null,
   "_user_tags": null,
   "allow_on_submit": 0,
   "bold": 0,
   "collapsible": 0,
   "collapsible_depends_on": null,
   "columns": 0,
   "creation": "2020-06-19 11:11:11.167977",
   "default": "0",
   "depends_on": null,
   "description": "",
   "docstatus": 0,
   "dt": "Report",
   "fetch_from": null,
   "fetch_if_empty": 0,
   "fieldname": "acceptable_data_lag",
   "fieldtype": "Int",
   "hidden": 0,
   "idx": 21,
   "ignore_user_permissions": 0,
   "ignore_xss_filter": 0,
   "in_global_search": 0,
   "in_list_view": 0,
   "in_standard_filter": 0,
   "insert_after": "column_break_14",
   "label": "Acceptable Data Lag",
   "modified": "2020-06-19 11:11:11.167977",
   "modified_by": "Administrator",
   "name": "Report-acceptable_data_lag",
   "no_copy": 0,
   "options": null,
   "owner": "Administrator",
   "parent": null,
   "parentfield": null,
   "parenttype": null,
   "permlevel": 0,
   "precision": "",
   "print_hide": 0,
   "print_hide_if_no_value": 0,
   "print_width": "",
   "read_only": 0,
   "regex_pattern": "",
   "report_hide": 0,
   "reqd": 0,
   "search_index": 0,
   "translatable": 0,
   "unique": 0,
   "width": ""
  },
  {
   "_assign": null,
   "_comments": null,
   "_liked_by": null,
   "_user_tags": null,
   "allow_on_submit": 0,
   "bold": 0,
   "collapsible": 0,
   "collapsible_depends_on": null,
   "columns": 0,
   "creation": "2020-06-19 11:11:11.078866",
   "default": null,
   "depends_on": null,
   "description": null,
   "docstatus": 0,
   "dt": "Report",
   "fetch_from": null,
   "fetch_if_empty": 0,
   "fieldname": "column_break_14",
   "fieldtype": "Column Break",
   "hidden": 0,
   "idx": 19,
   "ignore_user_permissions": 0,
   "ignore_xss_filter": 0,
   "in_global_search": 0,
   "in_list_view": 0,
   "in_standard_filter": 0,
   "insert_after": "replica_priority",
   "label": "",
   "modified": "2020-06-19 11:11:11.078866",
   "modified_by": "Administrator",
   "name": "Report-column_break_14",
   "no_copy": 0,
   "options": null,
   "owner": "Administrator",
   "parent": null,
   "parentfield": null,
   "parenttype": null,
   "permlevel": 0,
   "precision": "",
   "print_hide": 0,
   "print_hide_if_no_value": 0,
   "print_width": "",
   "read_only": 0,
   "regex_pattern": "",
   "report_hide": 0,
   "reqd": 0,
   "search_index": 0,
   "translatable": 0,
   "unique": 0,
   "width": ""
  },
  {
   "_assign": null,
   "_comments": null,
   "_liked_by": null,
   "_user_tags": null,
   "allow_on_submit": 0,
   "bold": 0,
   "collapsible": 0,
   "collapsible_depends_on": null,
   "columns": 0,
   "creation": "2020-06-16 13:16:00.420988",
   "default": "60",
   "depends_on": null,
   "description": null,
   "docstatus": 0,
   "dt": "Report",
   "fetch_from": null,
   "fetch_if_empty": 0,
   "fieldname": "timeout",
   "fieldtype": "Int",
   "hidden": 0,
   "idx": 18,
   "ignore_user_permissions": 0,
   "ignore_xss_filter": 0,
   "in_global_search": 0,
   "in_list_view": 0,
   "in_standard_filter": 0,
   "insert_after": "datasource",
   "label": "Timeout",
   "modified": "2020-06-16 13:16:00.420988",
   "modified_by": "Administrator",
   "name": "Report-timeout",
   "no_copy": 0,
   "options": null,
   "owner": "Administrator",
   "parent": null,
   "parentfield": null,
   "parenttype": null,
   "permlevel": 0,
   "precision": "",
   "print_hide": 0,
   "print_hide_if_no_value": 0,
   "print_width": "",
   "read_only": 0,
   "regex_pattern": "",
   "report_hide": 0,
   "reqd": 0,
   "search_index": 0,
   "translatable": 0,
   "unique": 0,
   "width": ""
  },
  {
   "_assign": null,
   "_comments": null,
   "_liked_by": null,
   "_user_tags": null,
   "allow_on_submit": 0,
   "bold": 0,
   "collapsible": 1,
   "collapsible_depends_on": null,
   "columns": 0,
   "creation": "2020-06-16 13:16:00.338837",
   "default": null,
   "depends_on": null,
   "description": null,
   "docstatus": 0,
   "dt": "Report",
   "fetch_from": null,
   "fetch_if_empty": 0,
   "fieldname": "datasource_settings",
   "fieldtype": "Section Break",
   "hidden": 0,
   "idx": 16,
   "ignore_user_permissions": 0,
   "ignore_xss_filter": 0,
   "in_global_search": 0,
   "in_list_view": 0,
   "in_standard_filter": 0,
   "insert_after": "description",
   "label": "Datasource Settings",
   "modified": "2020-06-16 13:16:00.338837",
   "modified_by": "Administrator",
   "name": "Report-datasource_settings",
   "no_copy": 0,
   "options": null,
   "owner": "Administrator",
   "parent": null,
   "parentfield": null,
   "parenttype": null,
   "permlevel": 0,
   "precision": "",
   "print_hide": 0,
   "print_hide_if_no_value": 0,
   "print_width": "",
   "read_only": 0,
   "regex_pattern": "",
   "report_hide": 0,
   "reqd": 0,
   "search_index": 0,
   "translatable": 0,
   "unique": 0,
   "width": ""
  },
  {
   "_assign": null,
   "_comments": null,
   "_liked_by": null,
   "_user_tags": null,
   "allow_on_submit": 0,
   "bold": 0,
   "collapsible": 0,
   "collapsible_depends_on": null,
   "columns": 0,
   "creation": "2020-05-14 19:23:13.378685",
   "default": null,
   "depends_on": null,
   "description": null,
   "docstatus": 0,
   "dt": "Report",
   "fetch_from": null,
   "fetch_if_empty": 0,
   "fieldname": "datasource",
   "fieldtype": "Link",
   "hidden": 0,
   "idx": 17,
   "ignore_user_permissions": 0,
   "ignore_xss_filter": 0,
   "in_global_search": 0,
   "in_list_view": 0,
   "in_standard_filter": 0,
   "insert_after": "datasource_settings",
   "label": "Datasource",
   "modified": "2020-05-14 19:23:13.378685",
   "modified_by": "Administrator",
   "name": "Report-datasource",
   "no_copy": 0,
   "options": "Datasource",
   "owner": "Administrator",
   "parent": null,
   "parentfield": null,
   "parenttype": null,
   "permlevel": 0,
   "precision": "",
   "print_hide": 0,
   "print_hide_if_no_value": 0,
   "print_width": "",
   "read_only": 0,
   "regex_pattern": "",
   "report_hide": 0,
   "reqd": 0,
   "search_index": 0,
   "translatable": 0,
   "unique": 0,
   "width": ""
  },
  {
   "_assign": null,
   "_comments": null,
   "_liked_by": null,
   "_user_tags": null,
   "allow_on_submit": 0,
   "bold": 0,
   "collapsible": 0,
   "collapsible_depends_on": null,
   "columns": 0,
   "creation": "2020-01-02 14:38:46.530567",
   "default": null,
   "depends_on": null,
   "description": null,
   "docstatus": 0,
   "dt": "Report",
   "fetch_from": null,
   "fetch_if_empty": 0,
   "fieldname": "column_order",
   "fieldtype": "Data",
   "hidden": 0,
   "idx": 31,
   "ignore_user_permissions": 0,
   "ignore_xss_filter": 0,
   "in_global_search": 0,
   "in_list_view": 0,
   "in_standard_filter": 0,
   "insert_after": "pivot_column",
   "label": "Column Order",
   "modified": "2020-01-02 14:38:46.530567",
   "modified_by": "Administrator",
   "name": "Report-column_order",
   "no_copy": 0,
   "options": "",
   "owner": "Administrator",
   "parent": null,
   "parentfield": null,
   "parenttype": null,
   "permlevel": 0,
   "precision": "",
   "print_hide": 0,
   "print_hide_if_no_value": 0,
   "print_width": "",
   "read_only": 0,
   "regex_pattern": "",
   "report_hide": 0,
   "reqd": 0,
   "search_index": 0,
   "translatable": 0,
   "unique": 0,
   "width": ""
  },
  {
   "_assign": null,
   "_comments": null,
   "_liked_by": null,
   "_user_tags": null,
   "allow_on_submit": 0,
   "bold": 0,
   "collapsible": 0,
   "collapsible_depends_on": null,
   "columns": 0,
   "creation": "2020-01-02 14:37:43.507339",
   "default": "mean",
   "depends_on": null,
   "description": null,
   "docstatus": 0,
   "dt": "Report",
   "fetch_from": null,
   "fetch_if_empty": 0,
   "fieldname": "aggregate_function",
   "fieldtype": "Select",
   "hidden": 0,
   "idx": 34,
   "ignore_user_permissions": 0,
   "ignore_xss_filter": 0,
   "in_global_search": 0,
   "in_list_view": 0,
   "in_standard_filter": 0,
   "insert_after": "pivot_cell",
   "label": "Aggregate Function",
   "modified": "2020-01-02 14:37:43.507339",
   "modified_by": "Administrator",
   "name": "Report-aggregate_function",
   "no_copy": 0,
   "options": "mean\nsum\nmin\nmax\nfirst\ncount",
   "owner": "Administrator",
   "parent": null,
   "parentfield": null,
   "parenttype": null,
   "permlevel": 0,
   "precision": "",
   "print_hide": 0,
   "print_hide_if_no_value": 0,
   "print_width": "",
   "read_only": 0,
   "regex_pattern": "",
   "report_hide": 0,
   "reqd": 0,
   "search_index": 0,
   "translatable": 0,
   "unique": 0,
   "width": ""
  },
  {
   "_assign": null,
   "_comments": null,
   "_liked_by": null,
   "_user_tags": null,
   "allow_on_submit": 0,
   "bold": 0,
   "collapsible": 0,
   "collapsible_depends_on": null,
   "columns": 0,
   "creation": "2019-12-26 20:52:10.892352",
   "default": null,
   "depends_on": null,
   "description": null,
   "docstatus": 0,
   "dt": "Report",
   "fetch_from": null,
   "fetch_if_empty": 0,
   "fieldname": "pivot_index",
   "fieldtype": "Data",
   "hidden": 0,
   "idx": 29,
   "ignore_user_permissions": 0,
   "ignore_xss_filter": 0,
   "in_global_search": 0,
   "in_list_view": 0,
   "in_standard_filter": 0,
   "insert_after": "section_break_15",
   "label": "Pivot Index",
   "modified": "2019-12-26 20:52:10.892352",
   "modified_by": "Administrator",
   "name": "Report-pivot_index",
   "no_copy": 0,
   "options": null,
   "owner": "Administrator",
   "parent": null,
   "parentfield": null,
   "parenttype": null,
   "permlevel": 0,
   "precision": "",
   "print_hide": 0,
   "print_hide_if_no_value": 0,
   "print_width": "",
   "read_only": 0,
   "regex_pattern": "",
   "report_hide": 0,
   "reqd": 0,
   "search_index": 0,
   "translatable": 0,
   "unique": 0,
   "width": ""
  },
  {
   "_assign": null,
   "_comments": null,
   "_liked_by": null,
   "_user_tags": null,
   "allow_on_submit": 0,
   "bold": 0,
   "collapsible": 0,
   "collapsible_depends_on": null,
   "columns": 0,
   "creation": "2019-12-26 20:05:01.824828",
   "default": null,
   "depends_on": null,
   "description": null,
   "docstatus": 0,
   "dt": "Report",
   "fetch_from": null,
   "fetch_if_empty": 0,
   "fieldname": "pivot_column",
   "fieldtype": "Data",
   "hidden": 0,
   "idx": 30,
   "ignore_user_permissions": 0,
   "ignore_xss_filter": 0,
   "in_global_search": 0,
   "in_list_view": 0,
   "in_standard_filter": 0,
   "insert_after": "pivot_index",
   "label": "Pivot Column",
   "modified": "2019-12-26 20:05:01.824828",
   "modified_by": "Administrator",
   "name": "Report-pivot_column",
   "no_copy": 0,
   "options": null,
   "owner": "Administrator",
   "parent": null,
   "parentfield": null,
   "parenttype": null,
   "permlevel": 0,
   "precision": "",
   "print_hide": 0,
   "print_hide_if_no_value": 0,
   "print_width": "",
   "read_only": 0,
   "regex_pattern": "",
   "report_hide": 0,
   "reqd": 0,
   "search_index": 0,
   "translatable": 0,
   "unique": 0,
   "width": ""
  },
  {
   "_assign": null,
   "_comments": null,
   "_liked_by": null,
   "_user_tags": null,
   "allow_on_submit": 0,
   "bold": 0,
   "collapsible": 0,
   "collapsible_depends_on": null,
   "columns": 0,
   "creation": "2019-12-26 19:59:48.994293",
   "default": null,
   "depends_on": null,
   "description": null,
   "docstatus": 0,
   "dt": "Report",
   "fetch_from": null,
   "fetch_if_empty": 0,
   "fieldname": "pivot_cell",
   "fieldtype": "Data",
   "hidden": 0,
   "idx": 33,
   "ignore_user_permissions": 0,
   "ignore_xss_filter": 0,
   "in_global_search": 0,
   "in_list_view": 0,
   "in_standard_filter": 0,
   "insert_after": "column_break_17",
   "label": "Pivot Cell",
   "modified": "2019-12-26 19:59:48.994293",
   "modified_by": "Administrator",
   "name": "Report-pivot_cell",
   "no_copy": 0,
   "options": null,
   "owner": "Administrator",
   "parent": null,
   "parentfield": null,
   "parenttype": null,
   "permlevel": 0,
   "precision": "",
   "print_hide": 0,
   "print_hide_if_no_value": 0,
   "print_width": "",
   "read_only": 0,
   "regex_pattern": "",
   "report_hide": 0,
   "reqd": 0,
   "search_index": 0,
   "translatable": 0,
   "unique": 0,
   "width": ""
  },
  {
   "_assign": null,
   "_comments": null,
   "_liked_by": null,
   "_user_tags": null,
   "allow_on_submit": 0,
   "bold": 0,
   "collapsible": 0,
   "collapsible_depends_on": null,
   "columns": 0,
   "creation": "2019-12-26 19:59:48.794902",
   "default": null,
   "depends_on": null,
   "description": null,
   "docstatus": 0,
   "dt": "Report",
   "fetch_from": null,
   "fetch_if_empty": 0,
   "fieldname": "column_break_17",
   "fieldtype": "Column Break",
   "hidden": 0,
   "idx": 32,
   "ignore_user_permissions": 0,
   "ignore_xss_filter": 0,
   "in_global_search": 0,
   "in_list_view": 0,
   "in_standard_filter": 0,
   "insert_after": "column_order",
   "label": "",
   "modified": "2019-12-26 19:59:48.794902",
   "modified_by": "Administrator",
   "name": "Report-column_break_17",
   "no_copy": 0,
   "options": null,
   "owner": "Administrator",
   "parent": null,
   "parentfield": null,
   "parenttype": null,
   "permlevel": 0,
   "precision": "",
   "print_hide": 0,
   "print_hide_if_no_value": 0,
   "print_width": "",
   "read_only": 0,
   "regex_pattern": "",
   "report_hide": 0,
   "reqd": 0,
   "search_index": 0,
   "translatable": 0,
   "unique": 0,
   "width": ""
  },
  {
   "_assign": null,
   "_comments": null,
   "_liked_by": null,
   "_user_tags": null,
   "allow_on_submit": 0,
   "bold": 0,
   "collapsible": 0,
   "collapsible_depends_on": null,
   "columns": 0,
   "creation": "2019-12-26 19:59:43.550520",
   "default": null,
   "depends_on": null,
   "description": null,
   "docstatus": 0,
   "dt": "Report",
   "fetch_from": null,
   "fetch_if_empty": 0,
   "fieldname": "section_break_15",
   "fieldtype": "Section Break",
   "hidden": 0,
   "idx": 28,
   "ignore_user_permissions": 0,
   "ignore_xss_filter": 0,
   "in_global_search": 0,
   "in_list_view": 0,
   "in_standard_filter": 0,
   "insert_after": "json",
   "label": "",
   "modified": "2019-12-26 19:59:43.550520",
   "modified_by": "Administrator",
   "name": "Report-section_break_15",
   "no_copy": 0,
   "options": null,
   "owner": "Administrator",
   "parent": null,
   "parentfield": null,
   "parenttype": null,
   "permlevel": 0,
   "precision": "",
   "print_hide": 0,
   "print_hide_if_no_value": 0,
   "print_width": "",
   "read_only": 0,
   "regex_pattern": "",
   "report_hide": 0,
   "reqd": 0,
   "search_index": 0,
   "translatable": 0,
   "unique": 0,
   "width": ""
  }
 ],
 "custom_perms": [
  {
   "_assign": null,
   "_comments": null,
   "_liked_by": null,
   "_user_tags": null,
   "amend": 0,
   "cancel": 0,
   "create": 0,
   "creation": "2013-03-09 15:45:57",
   "delete": 0,
   "docstatus": 0,
   "email": 1,
   "export": 0,
   "idx": 1,
   "if_owner": 0,
   "import": 0,
   "modified": "2017-11-02 13:01:45.661240",
   "modified_by": "edison.raj@elastic.run",
   "name": "7e4c6ac7f8",
   "owner": "Administrator",
   "parent": "Report",
   "parentfield": "permissions",
   "parenttype": "DocType",
   "permlevel": 0,
   "print": 0,
   "read": 1,
   "report": 1,
   "role": "Administrator",
   "set_user_permissions": 0,
   "share": 1,
   "submit": 0,
   "user_permission_doctypes": null,
   "write": 0
  },
  {
   "_assign": null,
   "_comments": null,
   "_liked_by": null,
   "_user_tags": null,
   "amend": 0,
   "cancel": 0,
   "create": 1,
   "creation": "2013-03-09 15:45:57",
   "delete": 1,
   "docstatus": 0,
   "email": 1,
   "export": 0,
   "idx": 3,
   "if_owner": 0,
   "import": 0,
   "modified": "2017-11-02 13:01:45.677129",
   "modified_by": "edison.raj@elastic.run",
   "name": "201d896328",
   "owner": "Administrator",
   "parent": "Report",
   "parentfield": "permissions",
   "parenttype": "DocType",
   "permlevel": 0,
   "print": 1,
   "read": 1,
   "report": 1,
   "role": "Report Manager",
   "set_user_permissions": 0,
   "share": 1,
   "submit": 0,
   "user_permission_doctypes": null,
   "write": 1
  },
  {
   "_assign": null,
   "_comments": null,
   "_liked_by": null,
   "_user_tags": null,
   "amend": 0,
   "cancel": 0,
   "create": 1,
   "creation": "2013-03-09 15:45:57",
   "delete": 1,
   "docstatus": 0,
   "email": 1,
   "export": 0,
   "idx": 2,
   "if_owner": 0,
   "import": 0,
   "modified": "2017-11-02 13:01:45.681220",
   "modified_by": "edison.raj@elastic.run",
   "name": "e0c5c9b531",
   "owner": "Administrator",
   "parent": "Report",
   "parentfield": "permissions",
   "parenttype": "DocType",
   "permlevel": 0,
   "print": 1,
   "read": 1,
   "report": 1,
   "role": "System Manager",
   "set_user_permissions": 0,
   "share": 1,
   "submit": 0,
   "user_permission_doctypes": null,
   "write": 1
  },
  {
   "_assign": null,
   "_comments": null,
   "_liked_by": null,
   "_user_tags": null,
   "amend": 0,
   "cancel": 0,
   "create": 0,
   "creation": "2017-11-02 13:01:45.690022",
   "delete": 0,
   "docstatus": 0,
   "email": 0,
   "export": 1,
   "idx": 0,
   "if_owner": 0,
   "import": 0,
   "modified": "2017-11-02 13:01:45.690022",
   "modified_by": "edison.raj@elastic.run",
   "name": "c64294488f",
   "owner": "edison.raj@elastic.run",
   "parent": "Report",
   "parentfield": "permissions",
   "parenttype": "DocType",
   "permlevel": 0,
   "print": 0,
   "read": 1,
   "report": 0,
   "role": "Sales User",
   "set_user_permissions": 0,
   "share": 1,
   "submit": 0,
   "user_permission_doctypes": null,
   "write": 0
  },
  {
   "_assign": null,
   "_comments": null,
   "_liked_by": null,
   "_user_tags": null,
   "amend": 0,
   "cancel": 0,
   "create": 0,
   "creation": "2018-02-12 12:26:17.070090",
   "delete": 0,
   "docstatus": 0,
   "email": 0,
   "export": 1,
   "idx": 0,
   "if_owner": 0,
   "import": 0,
   "modified": "2018-02-12 12:26:17.070090",
   "modified_by": "sagar.tiparadi@elastic.run",
   "name": "9aa83a8262",
   "owner": "sagar.tiparadi@elastic.run",
   "parent": "Report",
   "parentfield": "permissions",
   "parenttype": "DocType",
   "permlevel": 0,
   "print": 0,
   "read": 1,
   "report": 1,
   "role": "Retail Sales User",
   "set_user_permissions": 0,
   "share": 1,
   "submit": 0,
   "user_permission_doctypes": null,
   "write": 0
  },
  {
   "_assign": null,
   "_comments": null,
   "_liked_by": null,
   "_user_tags": null,
   "amend": 0,
   "cancel": 0,
   "create": 0,
   "creation": "2018-03-02 09:17:59.683517",
   "delete": 0,
   "docstatus": 0,
   "email": 0,
   "export": 0,
   "idx": 0,
   "if_owner": 0,
   "import": 0,
   "modified": "2018-03-02 09:17:59.683517",
   "modified_by": "Administrator",
   "name": "2e406ab95f",
   "owner": "Administrator",
   "parent": "Report",
   "parentfield": "permissions",
   "parenttype": "DocType",
   "permlevel": 0,
   "print": 0,
   "read": 1,
   "report": 0,
   "role": "All",
   "set_user_permissions": 0,
   "share": 0,
   "submit": 0,
   "user_permission_doctypes": null,
   "write": 0
  },
  {
   "_assign": null,
   "_comments": null,
   "_liked_by": null,
   "_user_tags": null,
   "amend": 0,
   "cancel": 0,
   "create": 0,
   "creation": "2018-04-25 22:26:20.051505",
   "delete": 0,
   "docstatus": 0,
   "email": 0,
   "export": 1,
   "idx": 0,
   "if_owner": 0,
   "import": 0,
   "modified": "2018-04-25 22:26:20.051505",
   "modified_by": "Administrator",
   "name": "0d75065c56",
   "owner": "Administrator",
   "parent": "Report",
   "parentfield": "permissions",
   "parenttype": "DocType",
   "permlevel": 0,
   "print": 0,
   "read": 1,
   "report": 1,
   "role": "Station Manager",
   "set_user_permissions": 0,
   "share": 1,
   "submit": 0,
   "user_permission_doctypes": null,
   "write": 0
  },
  {
   "_assign": null,
   "_comments": null,
   "_liked_by": null,
   "_user_tags": null,
   "amend": 0,
   "cancel": 0,
   "create": 0,
   "creation": "2019-01-18 11:15:01.503497",
   "delete": 0,
   "docstatus": 0,
   "email": 0,
   "export": 0,
   "idx": 0,
   "if_owner": 0,
   "import": 0,
   "modified": "2019-01-18 11:15:01.503497",
   "modified_by": "sagar.shiragawakar@elastic.run",
   "name": "357caaff7e",
   "owner": "sagar.shiragawakar@elastic.run",
   "parent": "Report",
   "parentfield": "permissions",
   "parenttype": "DocType",
   "permlevel": 0,
   "print": 0,
   "read": 1,
   "report": 0,
   "role": "SM",
   "set_user_permissions": 0,
   "share": 1,
   "submit": 0,
   "user_permission_doctypes": null,
   "write": 0
  }
 ],
 "doctype": "Report",
 "property_setters": [
  {
   "_assign": null,
   "_comments": null,
   "_liked_by": null,
   "_user_tags": null,
   "creation": "2021-05-28 19:43:17.903043",
   "default_value": "",
   "doc_type": "Report",
   "docstatus": 0,
   "doctype_or_field": "DocType",
   "field_name": "",
   "idx": 0,
   "modified": "2021-05-28 19:43:17.903043",
   "modified_by": "Administrator",
   "name": "Report-read_only_onload",
   "owner": "Administrator",
   "parent": null,
   "parentfield": null,
   "parenttype": null,
   "property": "read_only_onload",
   "property_type": "Check",
   "value": null
  },
  {
   "_assign": null,
   "_comments": null,
   "_liked_by": null,
   "_user_tags": null,
   "creation": "2020-06-16 13:16:00.315314",
   "default_value": "",
   "doc_type": "Report",
   "docstatus": 0,
   "doctype_or_field": "DocType",
   "field_name": "",
   "idx": 0,
   "modified": "2020-06-16 13:16:00.315314",
   "modified_by": "Administrator",
   "name": "Report-default_print_format",
   "owner": "Administrator",
   "parent": null,
   "parentfield": null,
   "parenttype": null,
   "property": "default_print_format",
   "property_type": "Data",
   "value": ""
  },
  {
   "_assign": null,
   "_comments": null,
   "_liked_by": null,
   "_user_tags": null,
   "creation": "2020-06-16 13:16:00.312496",
   "default_value": "",
   "doc_type": "Report",
   "docstatus": 0,
   "doctype_or_field": "DocType",
   "field_name": "",
   "idx": 0,
   "modified": "2020-06-16 13:16:00.312496",
   "modified_by": "Administrator",
   "name": "Report-image_field",
   "owner": "Administrator",
   "parent": null,
   "parentfield": null,
   "parenttype": null,
   "property": "image_field",
   "property_type": "Data",
   "value": ""
  },
  {
   "_assign": null,
   "_comments": null,
   "_liked_by": null,
   "_user_tags": null,
   "creation": "2020-06-16 13:16:00.310023",
   "default_value": "",
   "doc_type": "Report",
   "docstatus": 0,
   "doctype_or_field": "DocType",
   "field_name": "",
   "idx": 0,
   "modified": "2020-06-16 13:16:00.310023",
   "modified_by": "Administrator",
   "name": "Report-title_field",
   "owner": "Administrator",
   "parent": null,
   "parentfield": null,
   "parenttype": null,
   "property": "title_field",
   "property_type": "Data",
   "value": ""
  },
  {
   "_assign": null,
   "_comments": null,
   "_liked_by": null,
   "_user_tags": null,
   "creation": "2020-06-16 13:16:00.303540",
   "default_value": "",
   "doc_type": "Report",
   "docstatus": 0,
   "doctype_or_field": "DocType",
   "field_name": "",
   "idx": 0,
   "modified": "2020-06-16 13:16:00.303540",
   "modified_by": "Administrator",
   "name": "Report-search_fields",
   "owner": "Administrator",
   "parent": null,
   "parentfield": null,
   "parenttype": null,
   "property": "search_fields",
   "property_type": "Data",
   "value": ""
  },
  {
   "_assign": null,
   "_comments": null,
   "_liked_by": null,
   "_user_tags": null,
   "creation": "2019-11-14 20:04:30.415053",
   "default_value": "",
   "doc_type": "Report",
   "docstatus": 0,
   "doctype_or_field": "DocField",
   "field_name": "report_type",
   "idx": 0,
   "modified": "2019-11-14 20:04:30.415053",
   "modified_by": "Administrator",
   "name": "Report-report_type-options",
   "owner": "Administrator",
   "parent": null,
   "parentfield": null,
   "parenttype": null,
   "property": "options",
   "property_type": "Text",
   "value": "Report Builder\nQuery Report\nScript Report\nCustom Report\nJupyter Report"
  },
  {
   "_assign": null,
   "_comments": null,
   "_liked_by": null,
   "_user_tags": null,
   "creation": "2018-08-22 16:03:52.340641",
   "default_value": "",
   "doc_type": "Report",
   "docstatus": 0,
   "doctype_or_field": "DocType",
   "field_name": "",
   "idx": 0,
   "modified": "2018-08-22 16:03:52.340641",
   "modified_by": "Administrator",
   "name": "Report-track_changes",
   "owner": "Administrator",
   "parent": null,
   "parentfield": null,
   "parenttype": null,
   "property": "track_changes",
   "property_type": "Check",
   "value": "0"
  },
  {
   "_assign": null,
   "_comments": null,
   "_liked_by": null,
   "_user_tags": null,
   "creation": "2018-04-20 11:23:27.035346",
   "default_value": "",
   "doc_type": "Report",
   "docstatus": 0,
   "doctype_or_field": "DocField",
   "field_name": "javascript",
   "idx": 0,
   "modified": "2018-04-20 11:23:27.035346",
   "modified_by": "Administrator",
   "name": "Report-javascript-hidden",
   "owner": "Administrator",
   "parent": null,
   "parentfield": null,
   "parenttype": null,
   "property": "hidden",
   "property_type": "Check",
   "value": "0"
  }
 ],
 "sync_on_migrate": 1
}